optiML/__init__.py
optiML/import_file.py
optiML/preprocessing_data.py
optiML/preprocessing_data_expert_mode.py
optiML/pyoptiml.py
optiML/savefile.py
optiML/testing.py
optiML/trainingtesting.py
pyoptiML-0.3.dist-info/LICENSE
pyoptiML-0.3.dist-info/METADATA
pyoptiML-0.3.dist-info/WHEEL
pyoptiML-0.3.dist-info/top_level.txt
pyoptiML-0.3.dist-info/RECORD
