Metadata-Version: 2.1
Name: pyoptiML
Version: 0.3
Summary: A Machine Learning package for generating model
Home-page: https://github.com/alex-christopher/pyoptiML
Author: alex-christopher
Author-email: alexchristopher154@gmail.com
License: MIT
Project-URL: Bug Tracker, https://github.com/alex-christopher/pyoptiML/issues
Classifier: Programming Language :: Python :: 3.8
Classifier: Programming Language :: Python :: 3.9
Classifier: Programming Language :: Python :: 3.10
Classifier: Programming Language :: Python :: 3.11
Classifier: Operating System :: OS Independent
Requires-Python: >=3.7
License-File: LICENSE
Requires-Dist: ensure (==1.0.2)
Provides-Extra: testing
Requires-Dist: numpy (>=1.24.0) ; extra == 'testing'
Requires-Dist: pandas (>=1.5.3) ; extra == 'testing'
Requires-Dist: scikit-learn (>=1.1.0) ; extra == 'testing'
Requires-Dist: pytest (>=7.2.1) ; extra == 'testing'
Requires-Dist: mypy (>=0.971) ; extra == 'testing'
Requires-Dist: flake8 (>=5.0.4) ; extra == 'testing'
Requires-Dist: tox (>=4.4.6) ; extra == 'testing'
Requires-Dist: black (>=23.1.0) ; extra == 'testing'
Requires-Dist: ensure (>=1.0.2) ; extra == 'testing'
Requires-Dist: pyfiglet (==0.8.post1) ; extra == 'testing'
